uzvb/__init__.py
uzvb/common.py
uzvb/uzvb.py
uzvb-0.0.1.dist-info/LICENSE
uzvb-0.0.1.dist-info/METADATA
uzvb-0.0.1.dist-info/WHEEL
uzvb-0.0.1.dist-info/entry_points.txt
uzvb-0.0.1.dist-info/top_level.txt
uzvb-0.0.1.dist-info/RECORD
